stat_api/__init__.py
stat_api/helpers.py
stat_api/stat_api.py
stat_api/test.py
stat_api-0.5.dist-info/DESCRIPTION.rst
stat_api-0.5.dist-info/METADATA
stat_api-0.5.dist-info/metadata.json
stat_api-0.5.dist-info/RECORD
stat_api-0.5.dist-info/top_level.txt
stat_api-0.5.dist-info/WHEEL
